<?xml version="1.0"?>
<Primitives xmlns:xsd="http://www.w3.org/2001/XMLSchema" xmlns:xsi="http://www.w3.org/2001/XMLSchema-instance">
  <Arcs>
    <Arc Cx="33089335" Cy="33699418" Radius="0.08" SAngle="180" EAngle="270" Layer="68" Width="50000" />
    <Arc Cx="32979098" Cy="34140363" Radius="0.2" SAngle="0" EAngle="90.000000000000128" Layer="68" Width="50000" />
    <Arc Cx="30752094" Cy="34266435" Radius="0.0756" SAngle="169.8892755332958" EAngle="179.33227050529482" Layer="68" Width="50000" />
    <Arc Cx="30753816" Cy="34266371" Radius="0.07994" SAngle="89.984098698384145" EAngle="170.32508117758925" Layer="68" Width="50000" />
    <Arc Cx="31607499" Cy="34266347" Radius="0.08" SAngle="0" EAngle="0.82223191932504724" Layer="68" Width="50000" />
    <Arc Cx="29331615" Cy="33699418" Radius="0.08" SAngle="270" EAngle="360" Layer="68" Width="50000" />
    <Arc Cx="29441851" Cy="34140363" Radius="0.2" SAngle="90" EAngle="180" Layer="68" Width="50000" />
    <Arc Cx="30753767" Cy="34267081" Radius="0.07814" SAngle="89.892483888907208" EAngle="108.15280347001914" Layer="68" Width="50000" />
    <Arc Cx="30753826" Cy="34266346" Radius="0.08" SAngle="116.75590286567454" EAngle="179.20785540027038" Layer="68" Width="50000" />
    <Arc Cx="30752700" Cy="34268806" Radius="0.07314" SAngle="107.2038322970959" EAngle="116.95770219778672" Layer="68" Width="50000" />
    <Arc Cx="30770492" Cy="34266347" Radius="0.08" SAngle="90.000000000000014" EAngle="180" Layer="68" Width="50000" />
    <Arc Cx="30753826" Cy="34266346" Radius="0.08" SAngle="116.76618693501261" EAngle="179.23783395527059" Layer="68" Width="50000" />
    <Arc Cx="30752723" Cy="34268752" Radius="0.07329" SAngle="107.22472639734355" EAngle="116.96313560046929" Layer="68" Width="50000" />
    <Arc Cx="30753768" Cy="34267065" Radius="0.07818" SAngle="89.8950800664518" EAngle="108.15197118382265" Layer="68" Width="50000" />
    <Arc Cx="30753825" Cy="34266347" Radius="0.08" SAngle="108.38101436421066" EAngle="180.00000000000253" Layer="68" Width="50000" />
    <Arc Cx="30753825" Cy="34266347" Radius="0.08" SAngle="90.000000000000313" EAngle="180" Layer="68" Width="50000" />
    <Arc Cx="31607500" Cy="34266347" Radius="0.08" SAngle="0" EAngle="90" Layer="68" Width="50000" />
    <Arc Cx="30753824" Cy="34266347" Radius="0.08" SAngle="90" EAngle="180" Layer="68" Width="50000" />
    <Arc Cx="39769751" Cy="27296250" Radius="3.80988" SAngle="193.7874689431849" EAngle="196.17873351449546" Layer="68" Width="50000" />
    <Arc Cx="38578895" Cy="26740712" Radius="0.42324" SAngle="232.3082279893564" EAngle="253.06065692256138" Layer="68" Width="50000" />
    <Arc Cx="39455596" Cy="27204917" Radius="2.97888" SAngle="196.16990328831707" EAngle="198.98750017915992" Layer="68" Width="50000" />
    <Arc Cx="39201706" Cy="27117369" Radius="2.29674" SAngle="198.97615910359497" EAngle="202.32727756730034" Layer="68" Width="50000" />
    <Arc Cx="39001689" Cy="27035038" Radius="1.74734" SAngle="202.31294342370259" EAngle="206.33424178580282" Layer="68" Width="50000" />
    <Arc Cx="38849153" Cy="26959361" Radius="1.31484" SAngle="206.31682470772196" EAngle="211.17786180515893" Layer="68" Width="50000" />
    <Arc Cx="38737707" Cy="26891773" Radius="0.98377" SAngle="211.15848701253131" EAngle="217.05704023462809" Layer="68" Width="50000" />
    <Arc Cx="38660957" Cy="26833707" Radius="0.73932" SAngle="217.03962857606643" EAngle="224.17621493932404" Layer="68" Width="50000" />
    <Arc Cx="38612512" Cy="26786599" Radius="0.56769" SAngle="224.16948862792376" EAngle="232.68117272246687" Layer="68" Width="50000" />
    <Arc Cx="17703898" Cy="15403542" Radius="2" SAngle="346.04170992548859" EAngle="166.04170992548859" Layer="65" Width="236220" />
    <Arc Cx="20755079" Cy="13484251" Radius="2" SAngle="344.36750269694477" EAngle="164.36750269694471" Layer="65" Width="236220" />
    <Arc Cx="8353504" Cy="18405511" Radius="2" SAngle="328.36396400137244" EAngle="148.36396400137244" Layer="65" Width="236220" />
    <Arc Cx="14357441" Cy="17913385" Radius="2" SAngle="346.62866803010809" EAngle="166.62866803010809" Layer="65" Width="236220" />
    <Arc Cx="34731457" Cy="18061023" Radius="2" SAngle="17.549002229067781" EAngle="197.54900222906778" Layer="65" Width="236220" />
    <Arc Cx="30892874" Cy="15797243" Radius="2" SAngle="14.778161732937349" EAngle="194.77816173293735" Layer="65" Width="236220" />
    <Arc Cx="39652717" Cy="20669290" Radius="2" SAngle="40.81508387488158" EAngle="220.81508387488157" Layer="65" Width="236220" />
  </Arcs>
  <Tracks>
    <Track X1="35809082" Y1="34846758" X2="36061051" Y2="35098727" Layer="68" Width="50000" />
    <Track X1="36564988" Y1="35098727" X2="36816956" Y2="34846758" Layer="68" Width="50000" />
    <Track X1="36061051" Y1="35098727" X2="36564988" Y2="35098727" Layer="68" Width="50000" />
    <Track X1="31809084" Y1="34846758" X2="32061052" Y2="35098727" Layer="68" Width="50000" />
    <Track X1="32564989" Y1="35098727" X2="32816958" Y2="34846758" Layer="68" Width="50000" />
    <Track X1="32061052" Y1="35098727" X2="32564989" Y2="35098727" Layer="68" Width="50000" />
    <Track X1="24564988" Y1="35098727" X2="24816956" Y2="34846758" Layer="68" Width="50000" />
    <Track X1="24061051" Y1="35098727" X2="24564988" Y2="35098727" Layer="68" Width="50000" />
    <Track X1="26369924" Y1="35641150" X2="26449841" Y2="34485244" Layer="68" Width="50000" />
    <Track X1="27809082" Y1="34846758" X2="28061051" Y2="35098727" Layer="68" Width="50000" />
    <Track X1="28564988" Y1="35098727" X2="28816956" Y2="34846758" Layer="68" Width="50000" />
    <Track X1="28061051" Y1="35098727" X2="28564988" Y2="35098727" Layer="68" Width="50000" />
    <Track X1="23809082" Y1="34846758" X2="24061051" Y2="35098727" Layer="68" Width="50000" />
    <Track X1="18569526" Y1="34485244" X2="18649443" Y2="35641150" Layer="68" Width="50000" />
    <Track X1="15809082" Y1="34846758" X2="16061051" Y2="35098727" Layer="68" Width="50000" />
    <Track X1="16564988" Y1="35098727" X2="16816956" Y2="34846758" Layer="68" Width="50000" />
    <Track X1="16061051" Y1="35098727" X2="16564988" Y2="35098727" Layer="68" Width="50000" />
    <Track X1="11809082" Y1="34846758" X2="12061051" Y2="35098727" Layer="68" Width="50000" />
    <Track X1="12564988" Y1="35098727" X2="12816957" Y2="34846758" Layer="68" Width="50000" />
    <Track X1="12061051" Y1="35098727" X2="12564988" Y2="35098727" Layer="68" Width="50000" />
    <Track X1="19809082" Y1="34846758" X2="20061051" Y2="35098727" Layer="68" Width="50000" />
    <Track X1="20564988" Y1="35098727" X2="20816956" Y2="34846758" Layer="68" Width="50000" />
    <Track X1="20061051" Y1="35098727" X2="20564988" Y2="35098727" Layer="68" Width="50000" />
    <Track X1="18649443" Y1="35641150" X2="26369924" Y2="35641150" Layer="68" Width="50000" />
    <Track X1="19352683" Y1="35644300" X2="19352684" Y2="35641150" Layer="68" Width="50000" />
    <Track X1="19352684" Y1="35644300" X2="19509683" Y2="35644300" Layer="68" Width="50000" />
    <Track X1="19509683" Y1="35644300" X2="19666683" Y2="35644300" Layer="68" Width="50000" />
    <Track X1="19666683" Y1="35641150" X2="19666683" Y2="35644300" Layer="68" Width="50000" />
    <Track X1="9675040" Y1="30374316" X2="9675040" Y2="32880520" Layer="68" Width="50000" />
    <Track X1="12564990" Y1="16925498" X2="12816958" Y2="17177467" Layer="68" Width="50000" />
    <Track X1="11809084" Y1="17177467" X2="12816958" Y2="17177467" Layer="68" Width="50000" />
    <Track X1="10313020" Y1="26581311" X2="10313020" Y2="30374317" Layer="68" Width="50000" />
    <Track X1="11809084" Y1="17177467" X2="12061053" Y2="16925498" Layer="68" Width="50000" />
    <Track X1="10713020" Y1="26581311" X2="10713020" Y2="30374317" Layer="68" Width="50000" />
    <Track X1="12816957" Y1="24075107" X2="12816958" Y2="17177467" Layer="68" Width="50000" />
    <Track X1="12061053" Y1="16925498" X2="12564990" Y2="16925498" Layer="68" Width="50000" />
    <Track X1="11809083" Y1="24075107" X2="11809084" Y2="17177467" Layer="68" Width="50000" />
    <Track X1="20816957" Y1="24075107" X2="20816958" Y2="17177467" Layer="68" Width="50000" />
    <Track X1="20061052" Y1="16925498" X2="20564989" Y2="16925498" Layer="68" Width="50000" />
    <Track X1="16061053" Y1="16925498" X2="16564990" Y2="16925498" Layer="68" Width="50000" />
    <Track X1="16816957" Y1="24075107" X2="16816958" Y2="17177467" Layer="68" Width="50000" />
    <Track X1="15809083" Y1="24075107" X2="15809084" Y2="17177467" Layer="68" Width="50000" />
    <Track X1="16564990" Y1="16925498" X2="16816958" Y2="17177467" Layer="68" Width="50000" />
    <Track X1="15809084" Y1="17177467" X2="16816958" Y2="17177467" Layer="68" Width="50000" />
    <Track X1="15809084" Y1="17177467" X2="16061053" Y2="16925498" Layer="68" Width="50000" />
    <Track X1="19809083" Y1="24075107" X2="19809084" Y2="17177467" Layer="68" Width="50000" />
    <Track X1="20564989" Y1="16925498" X2="20816958" Y2="17177467" Layer="68" Width="50000" />
    <Track X1="19809084" Y1="17177467" X2="20816958" Y2="17177467" Layer="68" Width="50000" />
    <Track X1="19809084" Y1="17177467" X2="20061052" Y2="16925498" Layer="68" Width="50000" />
    <Track X1="23130156" Y1="34460048" X2="23809082" Y2="34460048" Layer="68" Width="50000" />
    <Track X1="23130156" Y1="33275796" X2="23809082" Y2="33275796" Layer="68" Width="50000" />
    <Track X1="23130156" Y1="33275796" X2="23809082" Y2="33275796" Layer="68" Width="50000" />
    <Track X1="25130156" Y1="33275796" X2="25889211" Y2="33275796" Layer="68" Width="50000" />
    <Track X1="25889211" Y1="33874221" X2="25889211" Y2="34460048" Layer="68" Width="50000" />
    <Track X1="25130156" Y1="34460048" X2="25889211" Y2="34460048" Layer="68" Width="50000" />
    <Track X1="25889211" Y1="33568709" X2="25889211" Y2="33874221" Layer="68" Width="50000" />
    <Track X1="25889211" Y1="33275796" X2="25889211" Y2="33568709" Layer="68" Width="50000" />
    <Track X1="25130156" Y1="33874221" X2="25130156" Y2="34460048" Layer="68" Width="50000" />
    <Track X1="26449841" Y1="34036426" X2="26449841" Y2="34485244" Layer="68" Width="50000" />
    <Track X1="18569526" Y1="34036426" X2="18569526" Y2="34485244" Layer="68" Width="50000" />
    <Track X1="19130156" Y1="34460048" X2="19809082" Y2="34460048" Layer="68" Width="50000" />
    <Track X1="19130156" Y1="33275796" X2="19130156" Y2="33568709" Layer="68" Width="50000" />
    <Track X1="18569526" Y1="34485244" X2="19809082" Y2="34485244" Layer="68" Width="50000" />
    <Track X1="18569526" Y1="34036426" X2="19130156" Y2="34036426" Layer="68" Width="50000" />
    <Track X1="20816956" Y1="34846758" X2="20816957" Y2="32880520" Layer="68" Width="50000" />
    <Track X1="20816956" Y1="34485244" X2="23809082" Y2="34485244" Layer="68" Width="50000" />
    <Track X1="21889211" Y1="34036426" X2="23130156" Y2="34036426" Layer="68" Width="50000" />
    <Track X1="23130156" Y1="32880520" X2="23130156" Y2="33275796" Layer="68" Width="50000" />
    <Track X1="23130156" Y1="33568709" X2="23130156" Y2="33874221" Layer="68" Width="50000" />
    <Track X1="23130156" Y1="33275796" X2="23130156" Y2="33568709" Layer="68" Width="50000" />
    <Track X1="23130156" Y1="33874221" X2="23130156" Y2="34460048" Layer="68" Width="50000" />
    <Track X1="19809082" Y1="34846758" X2="19809083" Y2="32880520" Layer="68" Width="50000" />
    <Track X1="19809082" Y1="34846758" X2="20816956" Y2="34846758" Layer="68" Width="50000" />
    <Track X1="24816956" Y1="32880520" X2="24816956" Y2="34846758" Layer="68" Width="50000" />
    <Track X1="23809082" Y1="34846758" X2="24816956" Y2="34846758" Layer="68" Width="50000" />
    <Track X1="23809082" Y1="32880520" X2="23809082" Y2="34846758" Layer="68" Width="50000" />
    <Track X1="33178979" Y1="33195481" X2="33178979" Y2="33667922" Layer="68" Width="50000" />
    <Track X1="32816958" Y1="34219103" X2="32821618" Y2="34219103" Layer="68" Width="50000" />
    <Track X1="32816958" Y1="32880520" X2="32816958" Y2="34846758" Layer="68" Width="50000" />
    <Track X1="32821618" Y1="34219103" X2="32979098" Y2="34219103" Layer="68" Width="50000" />
    <Track X1="32942758" Y1="33195481" X2="32942758" Y2="33667922" Layer="68" Width="50000" />
    <Track X1="32942758" Y1="33667922" X2="33178979" Y2="33667922" Layer="68" Width="50000" />
    <Track X1="33057838" Y1="33699418" X2="33057838" Y2="34140363" Layer="68" Width="50000" />
    <Track X1="32816958" Y1="33667922" X2="32942758" Y2="33667922" Layer="68" Width="50000" />
    <Track X1="31638995" Y1="34219103" X2="31638996" Y2="34266347" Layer="68" Width="50000" />
    <Track X1="30770492" Y1="34297843" X2="31607500" Y2="34297843" Layer="68" Width="50000" />
    <Track X1="30738996" Y1="34219103" X2="30738996" Y2="34266347" Layer="68" Width="50000" />
    <Track X1="30722328" Y1="34219103" X2="30722328" Y2="34266347" Layer="68" Width="50000" />
    <Track X1="29599332" Y1="34219103" X2="31809084" Y2="34219103" Layer="68" Width="50000" />
    <Track X1="9675040" Y1="32880520" X2="38808898" Y2="32880520" Layer="68" Width="50000" />
    <Track X1="19130156" Y1="33275796" X2="19809083" Y2="33275796" Layer="68" Width="50000" />
    <Track X1="32942758" Y1="33195481" X2="33178979" Y2="33195481" Layer="68" Width="50000" />
    <Track X1="32855136" Y1="33195481" X2="32942758" Y2="33195481" Layer="68" Width="50000" />
    <Track X1="32855136" Y1="32880520" X2="32855136" Y2="33195481" Layer="68" Width="50000" />
    <Track X1="32855136" Y1="33195481" X2="32942758" Y2="33195481" Layer="68" Width="50000" />
    <Track X1="32855136" Y1="32880520" X2="32855136" Y2="33195481" Layer="68" Width="50000" />
    <Track X1="32942758" Y1="33195481" X2="33178979" Y2="33195481" Layer="68" Width="50000" />
    <Track X1="33178979" Y1="32880520" X2="33178979" Y2="33195481" Layer="68" Width="50000" />
    <Track X1="32942758" Y1="32880520" X2="32942758" Y2="33195481" Layer="68" Width="50000" />
    <Track X1="29241971" Y1="32880520" X2="29241971" Y2="33195481" Layer="68" Width="50000" />
    <Track X1="29241971" Y1="32880520" X2="29241971" Y2="33195481" Layer="68" Width="50000" />
    <Track X1="18569526" Y1="34036426" X2="18689211" Y2="32880520" Layer="68" Width="50000" />
    <Track X1="19130156" Y1="33568709" X2="19130156" Y2="33874221" Layer="68" Width="50000" />
    <Track X1="19130156" Y1="33874221" X2="19130156" Y2="34460048" Layer="68" Width="50000" />
    <Track X1="29441851" Y1="34219103" X2="29599332" Y2="34219103" Layer="68" Width="50000" />
    <Track X1="27809082" Y1="34846758" X2="28816956" Y2="34846758" Layer="68" Width="50000" />
    <Track X1="30722328" Y1="34219103" X2="30722328" Y2="34266347" Layer="68" Width="50000" />
    <Track X1="30753825" Y1="34297843" X2="30770492" Y2="34297843" Layer="68" Width="50000" />
    <Track X1="29478191" Y1="33667922" X2="31809084" Y2="33667922" Layer="68" Width="50000" />
    <Track X1="29363111" Y1="33699418" X2="29363111" Y2="34140363" Layer="68" Width="50000" />
    <Track X1="29241971" Y1="33667922" X2="29478191" Y2="33667922" Layer="68" Width="50000" />
    <Track X1="27809082" Y1="32880520" X2="27809082" Y2="34846758" Layer="68" Width="50000" />
    <Track X1="28816956" Y1="32880520" X2="28816956" Y2="34846758" Layer="68" Width="50000" />
    <Track X1="31809084" Y1="32880520" X2="31809084" Y2="34846758" Layer="68" Width="50000" />
    <Track X1="31809084" Y1="34846758" X2="32816958" Y2="34846758" Layer="68" Width="50000" />
    <Track X1="29241971" Y1="32880520" X2="29241971" Y2="33195481" Layer="68" Width="50000" />
    <Track X1="29478191" Y1="33195481" X2="29478191" Y2="33667922" Layer="68" Width="50000" />
    <Track X1="29565814" Y1="32880520" X2="29565814" Y2="33195481" Layer="68" Width="50000" />
    <Track X1="29478191" Y1="33195481" X2="29478191" Y2="33667922" Layer="68" Width="50000" />
    <Track X1="29241971" Y1="33195481" X2="29478191" Y2="33195481" Layer="68" Width="50000" />
    <Track X1="29478191" Y1="33195481" X2="29565814" Y2="33195481" Layer="68" Width="50000" />
    <Track X1="29241971" Y1="33195481" X2="29241971" Y2="33667922" Layer="68" Width="50000" />
    <Track X1="29565814" Y1="32880520" X2="29565814" Y2="33195481" Layer="68" Width="50000" />
    <Track X1="29478190" Y1="32880520" X2="29478191" Y2="33195481" Layer="68" Width="50000" />
    <Track X1="29241971" Y1="33195481" X2="29478191" Y2="33195481" Layer="68" Width="50000" />
    <Track X1="29478191" Y1="33195481" X2="29565814" Y2="33195481" Layer="68" Width="50000" />
    <Track X1="15264963" Y1="32880520" X2="15264963" Y2="33510441" Layer="68" Width="50000" />
    <Track X1="15809082" Y1="34846758" X2="16816956" Y2="34846758" Layer="68" Width="50000" />
    <Track X1="15264963" Y1="33510441" X2="15659290" Y2="33510441" Layer="68" Width="50000" />
    <Track X1="15264963" Y1="33510441" X2="15659290" Y2="33510441" Layer="68" Width="50000" />
    <Track X1="15659290" Y1="32880520" X2="15659290" Y2="33510441" Layer="68" Width="50000" />
    <Track X1="15659290" Y1="33510441" X2="15809083" Y2="33510441" Layer="68" Width="50000" />
    <Track X1="39542560" Y1="24075107" X2="39542560" Y2="26581311" Layer="68" Width="50000" />
    <Track X1="38430942" Y1="26655349" X2="38430942" Y2="30374316" Layer="68" Width="50000" />
    <Track X1="37913019" Y1="30374317" X2="37913020" Y2="26581311" Layer="68" Width="50000" />
    <Track X1="38313019" Y1="30374317" X2="38313020" Y2="26581311" Layer="68" Width="50000" />
    <Track X1="34713019" Y1="30374317" X2="34713020" Y2="26581311" Layer="68" Width="50000" />
    <Track X1="30313021" Y1="26581311" X2="30313021" Y2="30374317" Layer="68" Width="50000" />
    <Track X1="34313021" Y1="26581311" X2="34313021" Y2="30374317" Layer="68" Width="50000" />
    <Track X1="33913021" Y1="26581311" X2="33913021" Y2="30374317" Layer="68" Width="50000" />
    <Track X1="30713021" Y1="26581311" X2="30713021" Y2="30374317" Layer="68" Width="50000" />
    <Track X1="34313021" Y1="26581311" X2="34313021" Y2="30374317" Layer="68" Width="50000" />
    <Track X1="29913020" Y1="26581311" X2="29913020" Y2="30374317" Layer="68" Width="50000" />
    <Track X1="30313021" Y1="26581311" X2="30313021" Y2="30374317" Layer="68" Width="50000" />
    <Track X1="38808898" Y1="30374316" X2="38808898" Y2="32880520" Layer="68" Width="50000" />
    <Track X1="35809084" Y1="17177467" X2="36061052" Y2="16925498" Layer="68" Width="50000" />
    <Track X1="36816957" Y1="24075107" X2="36816958" Y2="17177467" Layer="68" Width="50000" />
    <Track X1="36061052" Y1="16925498" X2="36564989" Y2="16925498" Layer="68" Width="50000" />
    <Track X1="35809083" Y1="24075107" X2="35809084" Y2="17177467" Layer="68" Width="50000" />
    <Track X1="36564989" Y1="16925498" X2="36816958" Y2="17177467" Layer="68" Width="50000" />
    <Track X1="35809084" Y1="17177467" X2="36816958" Y2="17177467" Layer="68" Width="50000" />
    <Track X1="26330156" Y1="32880520" X2="26449841" Y2="34036426" Layer="68" Width="50000" />
    <Track X1="25130156" Y1="33568709" X2="25130156" Y2="33874221" Layer="68" Width="50000" />
    <Track X1="25130156" Y1="32880520" X2="25130156" Y2="33275796" Layer="68" Width="50000" />
    <Track X1="25130156" Y1="33275796" X2="25889211" Y2="33275796" Layer="68" Width="50000" />
    <Track X1="25130156" Y1="33275796" X2="25130156" Y2="33568709" Layer="68" Width="50000" />
    <Track X1="24816956" Y1="34485244" X2="26449841" Y2="34485244" Layer="68" Width="50000" />
    <Track X1="24816956" Y1="34036426" X2="25130156" Y2="34036426" Layer="68" Width="50000" />
    <Track X1="25889211" Y1="34036426" X2="26449841" Y2="34036426" Layer="68" Width="50000" />
    <Track X1="8872675" Y1="24075107" X2="39542560" Y2="24075107" Layer="68" Width="50000" />
    <Track X1="8872675" Y1="24075107" X2="8872675" Y2="26581311" Layer="68" Width="50000" />
    <Track X1="9809713" Y1="26581311" X2="10037427" Y2="26581311" Layer="68" Width="50000" />
    <Track X1="25889211" Y1="32880520" X2="25889211" Y2="33275796" Layer="68" Width="50000" />
    <Track X1="9675040" Y1="30374316" X2="38808898" Y2="30374316" Layer="68" Width="50000" />
    <Track X1="21913020" Y1="26581311" X2="21913020" Y2="30374317" Layer="68" Width="50000" />
    <Track X1="25913020" Y1="26581311" X2="25913020" Y2="30374317" Layer="68" Width="50000" />
    <Track X1="26313020" Y1="26581311" X2="26313020" Y2="30374317" Layer="68" Width="50000" />
    <Track X1="26313020" Y1="26581311" X2="26313020" Y2="30374317" Layer="68" Width="50000" />
    <Track X1="26713020" Y1="26581311" X2="26713020" Y2="30374317" Layer="68" Width="50000" />
    <Track X1="22713020" Y1="26581311" X2="22713020" Y2="30374317" Layer="68" Width="50000" />
    <Track X1="22313020" Y1="26581311" X2="22313020" Y2="30374317" Layer="68" Width="50000" />
    <Track X1="22313020" Y1="26581311" X2="22313020" Y2="30374317" Layer="68" Width="50000" />
    <Track X1="14313020" Y1="26581311" X2="14313020" Y2="30374317" Layer="68" Width="50000" />
    <Track X1="17913020" Y1="26581311" X2="17913020" Y2="30374317" Layer="68" Width="50000" />
    <Track X1="18313020" Y1="26581311" X2="18313020" Y2="30374317" Layer="68" Width="50000" />
    <Track X1="14713020" Y1="26581311" X2="14713020" Y2="30374317" Layer="68" Width="50000" />
    <Track X1="13913020" Y1="26581311" X2="13913020" Y2="30374317" Layer="68" Width="50000" />
    <Track X1="14313020" Y1="26581311" X2="14313020" Y2="30374317" Layer="68" Width="50000" />
    <Track X1="8872675" Y1="26581311" X2="39542560" Y2="26581311" Layer="68" Width="50000" />
    <Track X1="10037427" Y1="26581311" X2="10313020" Y2="26581311" Layer="68" Width="50000" />
    <Track X1="18313020" Y1="26581311" X2="18313020" Y2="30374317" Layer="68" Width="50000" />
    <Track X1="18713020" Y1="26581311" X2="18713020" Y2="30374317" Layer="68" Width="50000" />
    <Track X1="32816959" Y1="17177467" X2="32816959" Y2="24075107" Layer="68" Width="50000" />
    <Track X1="28816957" Y1="24075107" X2="28816958" Y2="17177467" Layer="68" Width="50000" />
    <Track X1="32061054" Y1="16925498" X2="32564991" Y2="16925498" Layer="68" Width="50000" />
    <Track X1="31809085" Y1="17177467" X2="31809085" Y2="24075107" Layer="68" Width="50000" />
    <Track X1="32564991" Y1="16925498" X2="32816959" Y2="17177467" Layer="68" Width="50000" />
    <Track X1="31809085" Y1="17177467" X2="32816959" Y2="17177467" Layer="68" Width="50000" />
    <Track X1="31809085" Y1="17177467" X2="32061054" Y2="16925498" Layer="68" Width="50000" />
    <Track X1="28061052" Y1="16925498" X2="28564989" Y2="16925498" Layer="68" Width="50000" />
    <Track X1="27809083" Y1="24075107" X2="27809084" Y2="17177467" Layer="68" Width="50000" />
    <Track X1="28564989" Y1="16925498" X2="28816958" Y2="17177467" Layer="68" Width="50000" />
    <Track X1="27809084" Y1="17177467" X2="28816958" Y2="17177467" Layer="68" Width="50000" />
    <Track X1="27809084" Y1="17177467" X2="28061052" Y2="16925498" Layer="68" Width="50000" />
    <Track X1="23809083" Y1="24075107" X2="23809084" Y2="17177467" Layer="68" Width="50000" />
    <Track X1="24816957" Y1="24075107" X2="24816958" Y2="17177467" Layer="68" Width="50000" />
    <Track X1="24061052" Y1="16925498" X2="24564989" Y2="16925498" Layer="68" Width="50000" />
    <Track X1="24564989" Y1="16925498" X2="24816958" Y2="17177467" Layer="68" Width="50000" />
    <Track X1="23809084" Y1="17177467" X2="24816958" Y2="17177467" Layer="68" Width="50000" />
    <Track X1="23809084" Y1="17177467" X2="24061052" Y2="16925498" Layer="68" Width="50000" />
    <Track X1="11809082" Y1="34846758" X2="12816957" Y2="34846758" Layer="68" Width="50000" />
    <Track X1="15659290" Y1="33510441" X2="15809083" Y2="33510441" Layer="68" Width="50000" />
    <Track X1="15809082" Y1="34846758" X2="15809083" Y2="32880520" Layer="68" Width="50000" />
    <Track X1="16816956" Y1="34846758" X2="16816957" Y2="32880520" Layer="68" Width="50000" />
    <Track X1="12816957" Y1="32880520" X2="12816957" Y2="34846758" Layer="68" Width="50000" />
    <Track X1="11809082" Y1="34846758" X2="11809083" Y2="32880520" Layer="68" Width="50000" />
    <Track X1="21889211" Y1="32880520" X2="21889211" Y2="33275796" Layer="68" Width="50000" />
    <Track X1="19130156" Y1="33275796" X2="19809083" Y2="33275796" Layer="68" Width="50000" />
    <Track X1="19130156" Y1="32880520" X2="19130156" Y2="33275796" Layer="68" Width="50000" />
    <Track X1="21130156" Y1="33275796" X2="21889211" Y2="33275796" Layer="68" Width="50000" />
    <Track X1="21130156" Y1="32880520" X2="21130156" Y2="33275796" Layer="68" Width="50000" />
    <Track X1="21130156" Y1="33275796" X2="21130156" Y2="33568709" Layer="68" Width="50000" />
    <Track X1="21889211" Y1="33568709" X2="21889211" Y2="33874221" Layer="68" Width="50000" />
    <Track X1="21130156" Y1="33275796" X2="21889211" Y2="33275796" Layer="68" Width="50000" />
    <Track X1="21889211" Y1="33275796" X2="21889211" Y2="33568709" Layer="68" Width="50000" />
    <Track X1="21889211" Y1="33874221" X2="21889211" Y2="34460048" Layer="68" Width="50000" />
    <Track X1="21130156" Y1="33568709" X2="21130156" Y2="33874221" Layer="68" Width="50000" />
    <Track X1="21130156" Y1="34460048" X2="21889211" Y2="34460048" Layer="68" Width="50000" />
    <Track X1="21130156" Y1="33874221" X2="21130156" Y2="34460048" Layer="68" Width="50000" />
    <Track X1="20816956" Y1="34036426" X2="21130156" Y2="34036426" Layer="68" Width="50000" />
    <Track X1="35068734" Y1="32880520" X2="35068734" Y2="33510441" Layer="68" Width="50000" />
    <Track X1="37785276" Y1="32880520" X2="37785276" Y2="33510441" Layer="68" Width="50000" />
    <Track X1="35809082" Y1="34846758" X2="36816956" Y2="34846758" Layer="68" Width="50000" />
    <Track X1="36997875" Y1="33510441" X2="37785276" Y2="33510441" Layer="68" Width="50000" />
    <Track X1="36997875" Y1="32880520" X2="36997875" Y2="33510441" Layer="68" Width="50000" />
    <Track X1="36997875" Y1="33510441" X2="37785276" Y2="33510441" Layer="68" Width="50000" />
    <Track X1="35068734" Y1="33510441" X2="35809082" Y2="33510441" Layer="68" Width="50000" />
    <Track X1="36816956" Y1="32880520" X2="36816956" Y2="34846758" Layer="68" Width="50000" />
    <Track X1="35809082" Y1="32880520" X2="35809082" Y2="34846758" Layer="68" Width="50000" />
    <Track X1="35068734" Y1="33510441" X2="35809082" Y2="33510441" Layer="68" Width="50000" />
    <Track X1="17753111" Y1="2755905" X2="23757048" Y2="24212598" Layer="65" Width="70866" />
    <Track X1="15587757" Y1="6889763" X2="19820040" Y2="23917322" Layer="65" Width="70866" />
    <Track X1="10629922" Y1="6889763" X2="15587757" Y2="6889763" Layer="65" Width="70866" />
    <Track X1="12795276" Y1="2755905" X2="17753111" Y2="2755905" Layer="65" Width="70866" />
    <Track X1="4957835" Y1="12893700" X2="11749174" Y2="23917322" Layer="65" Width="70866" />
    <Track X1="12930276" Y1="11909448" X2="15784607" Y2="23917322" Layer="65" Width="70866" />
    <Track X1="0" Y1="12893700" X2="4957835" Y2="12893700" Layer="65" Width="70866" />
    <Track X1="7972441" Y1="11909448" X2="12930276" Y2="11909448" Layer="65" Width="70866" />
    <Track X1="32910591" Y1="23818897" X2="36552323" Y2="12303149" Layer="65" Width="70866" />
    <Track X1="33009016" Y1="7775590" X2="37966851" Y2="7775590" Layer="65" Width="70866" />
    <Track X1="28776733" Y1="23818897" X2="33009016" Y2="7775590" Layer="65" Width="70866" />
    <Track X1="36552323" Y1="12303149" X2="41510158" Y2="12303149" Layer="65" Width="70866" />
    <Track X1="36847599" Y1="23917322" X2="42457835" Y2="17421259" Layer="65" Width="70866" />
    <Track X1="42457835" Y1="17421259" X2="47415670" Y2="17421259" Layer="65" Width="70866" />
  </Tracks>
  <Texts>
    <Text X="11614174" Y="4133858" Italic="true" Size="7.68049" Rot="0" Mir="false" TrueType="true" Font="GlavkonGOST Type A" Layer="65" />
    <Text X="13779528" Y="0" Italic="true" Size="7.68049" Rot="0" Mir="false" TrueType="true" Font="GlavkonGOST Type A" Layer="65" />
    <Text X="984252" Y="10137795" Italic="true" Size="7.68049" Rot="0" Mir="false" TrueType="true" Font="GlavkonGOST Type A" Layer="65" />
    <Text X="8956693" Y="9153543" Italic="true" Size="7.68049" Rot="0" Mir="false" TrueType="true" Font="GlavkonGOST Type A" Layer="65" />
    <Text X="37536574" Y="9547244" Italic="true" Size="7.68049" Rot="0" Mir="false" TrueType="true" Font="GlavkonGOST Type A" Layer="65" />
    <Text X="33993267" Y="5019685" Italic="true" Size="7.68049" Rot="0" Mir="false" TrueType="true" Font="GlavkonGOST Type A" Layer="65" />
    <Text X="43442086" Y="14665354" Italic="true" Size="7.68049" Rot="0" Mir="false" TrueType="true" Font="GlavkonGOST Type A" Layer="65" />
  </Texts>
  <Regions>
    <Region Layer="65">
      <Points>
        <RegionPoint X="11749174" Y="23917322" />
        <RegionPoint X="10937297" Y="22105407" />
        <RegionPoint X="10819903" Y="22408941" />
        <RegionPoint X="10496003" Y="22377275" />
      </Points>
    </Region>
    <Region Layer="65">
      <Points>
        <RegionPoint X="15784607" Y="23917322" />
        <RegionPoint X="15581501" Y="21942245" />
        <RegionPoint X="15374892" Y="22193695" />
        <RegionPoint X="15077234" Y="22062112" />
      </Points>
    </Region>
    <Region Layer="65">
      <Points>
        <RegionPoint X="19820040" Y="23917322" />
        <RegionPoint X="19596712" Y="21944429" />
        <RegionPoint X="19392689" Y="22197983" />
        <RegionPoint X="19093699" Y="22069456" />
      </Points>
    </Region>
    <Region Layer="65">
      <Points>
        <RegionPoint X="23757048" Y="24212598" />
        <RegionPoint X="23476174" Y="22247072" />
        <RegionPoint X="23279647" Y="22506478" />
        <RegionPoint X="22977030" Y="22386741" />
      </Points>
    </Region>
    <Region Layer="65">
      <Points>
        <RegionPoint X="28776733" Y="23818897" />
        <RegionPoint X="29529439" Y="21981613" />
        <RegionPoint X="29228641" Y="22105849" />
        <RegionPoint X="29028268" Y="21849402" />
      </Points>
    </Region>
    <Region Layer="65">
      <Points>
        <RegionPoint X="32910591" Y="23818897" />
        <RegionPoint X="33751234" Y="22020148" />
        <RegionPoint X="33444782" Y="22129697" />
        <RegionPoint X="33257040" Y="21863864" />
      </Points>
    </Region>
    <Region Layer="65">
      <Points>
        <RegionPoint X="36847599" Y="23917322" />
        <RegionPoint X="38330390" Y="22596902" />
        <RegionPoint X="38005586" Y="22576494" />
        <RegionPoint X="37938116" Y="22258120" />
      </Points>
    </Region>
  </Regions>
  <Width>47415670</Width>
  <Height>35644300</Height>
</Primitives>